fastapi_sqlalchemy_ease/__init__.py
fastapi_sqlalchemy_ease/core.py
fastapi_sqlalchemy_ease/exceptions.py
fastapi_sqlalchemy_ease-0.1.4.dist-info/licenses/LICENSE
fastapi_sqlalchemy_ease-0.1.4.dist-info/METADATA
fastapi_sqlalchemy_ease-0.1.4.dist-info/WHEEL
fastapi_sqlalchemy_ease-0.1.4.dist-info/top_level.txt
fastapi_sqlalchemy_ease-0.1.4.dist-info/RECORD
