Metadata-Version: 2.4
Name: fastapi-sqlalchemy-ease
Version: 0.1.4
Summary: A reusable SQLAlchemy extension for FastAPI
Requires-Python: >=3.8
License-File: LICENSE
Requires-Dist: sqlalchemy>=2.0.0
Dynamic: description
Dynamic: description-content-type
Dynamic: license-file
Dynamic: requires-dist
Dynamic: requires-python
Dynamic: summary
